justconf/__init__.py
justconf/exception.py
justconf/loader.py
justconf/merge.py
justconf/process.py
justconf/py.typed
justconf/schema.py
justconf/processor/__init__.py
justconf/processor/base.py
justconf/processor/vault.py
justconf-0.2.0a4.dist-info/METADATA
justconf-0.2.0a4.dist-info/WHEEL
justconf-0.2.0a4.dist-info/licenses/LICENSE
justconf-0.2.0a4.dist-info/RECORD
