Metadata-Version: 2.4
Name: justconf
Version: 0.2.0a4
Summary: Minimal schema-agnostic configuration loader library
Project-URL: Documentation, https://aleksey925.github.io/justconf/
Project-URL: Homepage, https://github.com/aleksey925/justconf
Project-URL: Issues, https://github.com/aleksey925/justconf/issues
Project-URL: Repository, https://github.com/aleksey925/justconf
Author-email: Aleksey Petrunnik <petrunnik.a@gmail.com>
License-Expression: MIT
License-File: LICENSE
Keywords: config,configuration,dotenv,environment,secrets,settings,toml,vault
Classifier: Intended Audience :: Developers
Classifier: License :: OSI Approved :: MIT License
Classifier: Operating System :: OS Independent
Classifier: Programming Language :: Python :: 3 :: Only
Classifier: Programming Language :: Python :: 3.11
Classifier: Programming Language :: Python :: 3.12
Classifier: Programming Language :: Python :: 3.13
Classifier: Programming Language :: Python :: 3.14
Classifier: Topic :: Software Development :: Libraries :: Python Modules
Classifier: Typing :: Typed
Requires-Python: >=3.11
Provides-Extra: dotenv
Requires-Dist: python-dotenv>=1; extra == 'dotenv'
